{
  "chunks": [
    {
      "rendered": true,
      "initial": false,
      "entry": false,
      "recorded": false,
      "size": 67153,
      "sizes": {
        "javascript": 67153
      },
      "names": [],
      "idHints": [],
      "runtime": [
        "@openmrs/esm-patient-notes-app"
      ],
      "files": [
        "89.js"
      ],
      "auxiliaryFiles": [
        "89.js.map"
      ],
      "hash": "cd311c6a97be4ed5",
      "childrenByOrder": {}
    },
    {
      "rendered": true,
      "initial": false,
      "entry": false,
      "recorded": false,
      "reason": "reused as split chunk (cache group: defaultVendors)",
      "size": 1754991,
      "sizes": {
        "javascript": 1754991
      },
      "names": [],
      "idHints": [
        "vendors"
      ],
      "runtime": [
        "@openmrs/esm-patient-notes-app",
        "main"
      ],
      "files": [
        "130.js"
      ],
      "auxiliaryFiles": [
        "130.js.map"
      ],
      "hash": "751e354920497f90",
      "childrenByOrder": {}
    },
    {
      "rendered": true,
      "initial": false,
      "entry": false,
      "recorded": false,
      "size": 480,
      "sizes": {
        "javascript": 480
      },
      "names": [],
      "idHints": [],
      "runtime": [
        "@openmrs/esm-patient-notes-app",
        "main"
      ],
      "files": [
        "152.js"
      ],
      "auxiliaryFiles": [
        "152.js.map"
      ],
      "hash": "ece5dfb5ac7b3542",
      "childrenByOrder": {}
    },
    {
      "rendered": true,
      "initial": false,
      "entry": false,
      "recorded": false,
      "reason": "reused as split chunk (cache group: default)",
      "size": 118546,
      "sizes": {
        "javascript": 118420,
        "consume-shared": 126
      },
      "names": [],
      "idHints": [],
      "runtime": [
        "@openmrs/esm-patient-notes-app",
        "main"
      ],
      "files": [
        "161.js"
      ],
      "auxiliaryFiles": [
        "161.js.map"
      ],
      "hash": "95548cf087e03373",
      "childrenByOrder": {}
    },
    {
      "rendered": true,
      "initial": true,
      "entry": true,
      "recorded": false,
      "size": 2184294,
      "sizes": {
        "consume-shared": 210,
        "javascript": 2162288,
        "share-init": 336,
        "runtime": 21460
      },
      "names": [
        "main"
      ],
      "idHints": [],
      "runtime": [
        "main"
      ],
      "files": [
        "main.js"
      ],
      "auxiliaryFiles": [
        "main.js.map"
      ],
      "hash": "1c7799b90bdfb16c",
      "childrenByOrder": {}
    },
    {
      "rendered": true,
      "initial": false,
      "entry": false,
      "recorded": false,
      "reason": "split chunk (cache group: defaultVendors)",
      "size": 25337,
      "sizes": {
        "javascript": 25337
      },
      "names": [],
      "idHints": [
        "vendors"
      ],
      "runtime": [
        "@openmrs/esm-patient-notes-app",
        "main"
      ],
      "files": [
        "255.js"
      ],
      "auxiliaryFiles": [
        "255.js.map"
      ],
      "hash": "70b0452333842800",
      "childrenByOrder": {}
    },
    {
      "rendered": false,
      "initial": false,
      "entry": false,
      "recorded": false,
      "reason": "reused as split chunk (cache group: default)",
      "size": 42,
      "sizes": {
        "consume-shared": 42
      },
      "names": [],
      "idHints": [],
      "runtime": [
        "@openmrs/esm-patient-notes-app",
        "main"
      ],
      "files": [],
      "auxiliaryFiles": [],
      "hash": "bdaf6e26a74125c4",
      "childrenByOrder": {}
    },
    {
      "rendered": true,
      "initial": false,
      "entry": false,
      "recorded": false,
      "reason": "split chunk (cache group: defaultVendors)",
      "size": 241355,
      "sizes": {
        "javascript": 241355
      },
      "names": [],
      "idHints": [
        "vendors"
      ],
      "runtime": [
        "@openmrs/esm-patient-notes-app",
        "main"
      ],
      "files": [
        "271.js"
      ],
      "auxiliaryFiles": [
        "271.js.map"
      ],
      "hash": "1e0ca54eb859ecba",
      "childrenByOrder": {}
    },
    {
      "rendered": true,
      "initial": false,
      "entry": false,
      "recorded": false,
      "size": 480,
      "sizes": {
        "javascript": 480
      },
      "names": [],
      "idHints": [],
      "runtime": [
        "@openmrs/esm-patient-notes-app",
        "main"
      ],
      "files": [
        "303.js"
      ],
      "auxiliaryFiles": [
        "303.js.map"
      ],
      "hash": "569941963b7cacea",
      "childrenByOrder": {}
    },
    {
      "rendered": true,
      "initial": false,
      "entry": false,
      "recorded": false,
      "size": 1485,
      "sizes": {
        "javascript": 1485
      },
      "names": [],
      "idHints": [],
      "runtime": [
        "@openmrs/esm-patient-notes-app",
        "main"
      ],
      "files": [
        "319.js"
      ],
      "auxiliaryFiles": [],
      "hash": "2294995a58bc266a",
      "childrenByOrder": {}
    },
    {
      "rendered": false,
      "initial": false,
      "entry": false,
      "recorded": false,
      "reason": "split chunk (cache group: default)",
      "size": 42,
      "sizes": {
        "consume-shared": 42
      },
      "names": [],
      "idHints": [],
      "runtime": [
        "@openmrs/esm-patient-notes-app",
        "main"
      ],
      "files": [],
      "auxiliaryFiles": [],
      "hash": "b7e85561902d2629",
      "childrenByOrder": {}
    },
    {
      "rendered": true,
      "initial": false,
      "entry": false,
      "recorded": false,
      "size": 1237,
      "sizes": {
        "javascript": 1237
      },
      "names": [],
      "idHints": [],
      "runtime": [
        "@openmrs/esm-patient-notes-app",
        "main"
      ],
      "files": [
        "460.js"
      ],
      "auxiliaryFiles": [],
      "hash": "b41badc5a776fb66",
      "childrenByOrder": {}
    },
    {
      "rendered": true,
      "initial": false,
      "entry": false,
      "recorded": false,
      "size": 37693,
      "sizes": {
        "javascript": 37651,
        "consume-shared": 42
      },
      "names": [],
      "idHints": [],
      "runtime": [
        "@openmrs/esm-patient-notes-app",
        "main"
      ],
      "files": [
        "466.js"
      ],
      "auxiliaryFiles": [
        "466.js.map"
      ],
      "hash": "4144307493539b35",
      "childrenByOrder": {}
    },
    {
      "rendered": false,
      "initial": false,
      "entry": false,
      "recorded": false,
      "reason": "reused as split chunk (cache group: default)",
      "size": 126,
      "sizes": {
        "consume-shared": 126
      },
      "names": [],
      "idHints": [],
      "runtime": [
        "@openmrs/esm-patient-notes-app",
        "main"
      ],
      "files": [],
      "auxiliaryFiles": [],
      "hash": "510633fe1c601918",
      "childrenByOrder": {}
    },
    {
      "rendered": true,
      "initial": false,
      "entry": false,
      "recorded": false,
      "reason": "reused as split chunk (cache group: defaultVendors)",
      "size": 40147,
      "sizes": {
        "javascript": 40147
      },
      "names": [],
      "idHints": [
        "vendors"
      ],
      "runtime": [
        "@openmrs/esm-patient-notes-app",
        "main"
      ],
      "files": [
        "553.js"
      ],
      "auxiliaryFiles": [
        "553.js.map"
      ],
      "hash": "97b25eade6e2ff6a",
      "childrenByOrder": {}
    },
    {
      "rendered": true,
      "initial": false,
      "entry": false,
      "recorded": false,
      "size": 1286,
      "sizes": {
        "javascript": 1286
      },
      "names": [],
      "idHints": [],
      "runtime": [
        "@openmrs/esm-patient-notes-app",
        "main"
      ],
      "files": [
        "574.js"
      ],
      "auxiliaryFiles": [],
      "hash": "45f885adf3206dae",
      "childrenByOrder": {}
    },
    {
      "rendered": true,
      "initial": false,
      "entry": false,
      "recorded": false,
      "reason": "reused as split chunk (cache group: defaultVendors)",
      "size": 251616,
      "sizes": {
        "javascript": 251616
      },
      "names": [],
      "idHints": [
        "vendors"
      ],
      "runtime": [
        "@openmrs/esm-patient-notes-app",
        "main"
      ],
      "files": [
        "591.js"
      ],
      "auxiliaryFiles": [
        "591.js.map"
      ],
      "hash": "18c81af21bcac1fe",
      "childrenByOrder": {}
    },
    {
      "rendered": true,
      "initial": true,
      "entry": true,
      "recorded": false,
      "size": 21387,
      "sizes": {
        "javascript": 42,
        "share-init": 336,
        "runtime": 21009
      },
      "names": [
        "@openmrs/esm-patient-notes-app"
      ],
      "idHints": [],
      "runtime": [
        "@openmrs/esm-patient-notes-app"
      ],
      "files": [
        "openmrs-esm-patient-notes-app.js"
      ],
      "auxiliaryFiles": [
        "openmrs-esm-patient-notes-app.js.map"
      ],
      "hash": "3d36407810922a91",
      "childrenByOrder": {}
    },
    {
      "rendered": true,
      "initial": false,
      "entry": false,
      "recorded": false,
      "reason": "reused as split chunk (cache group: defaultVendors)",
      "size": 25530,
      "sizes": {
        "javascript": 25530
      },
      "names": [],
      "idHints": [
        "vendors"
      ],
      "runtime": [
        "@openmrs/esm-patient-notes-app",
        "main"
      ],
      "files": [
        "729.js"
      ],
      "auxiliaryFiles": [
        "729.js.map"
      ],
      "hash": "a059aae8ca7a159d",
      "childrenByOrder": {}
    },
    {
      "rendered": true,
      "initial": false,
      "entry": false,
      "recorded": false,
      "size": 1518,
      "sizes": {
        "javascript": 1518
      },
      "names": [],
      "idHints": [],
      "runtime": [
        "@openmrs/esm-patient-notes-app",
        "main"
      ],
      "files": [
        "757.js"
      ],
      "auxiliaryFiles": [],
      "hash": "8c353dd7391df61b",
      "childrenByOrder": {}
    },
    {
      "rendered": true,
      "initial": false,
      "entry": false,
      "recorded": false,
      "reason": "split chunk (cache group: defaultVendors)",
      "size": 2069798,
      "sizes": {
        "javascript": 2069798
      },
      "names": [],
      "idHints": [
        "vendors"
      ],
      "runtime": [
        "@openmrs/esm-patient-notes-app",
        "main"
      ],
      "files": [
        "765.js"
      ],
      "auxiliaryFiles": [
        "765.js.map"
      ],
      "hash": "b83e0e765c3bf85d",
      "childrenByOrder": {}
    },
    {
      "rendered": true,
      "initial": false,
      "entry": false,
      "recorded": false,
      "size": 7103,
      "sizes": {
        "javascript": 7103
      },
      "names": [],
      "idHints": [],
      "runtime": [
        "@openmrs/esm-patient-notes-app",
        "main"
      ],
      "files": [
        "784.js"
      ],
      "auxiliaryFiles": [
        "784.js.map"
      ],
      "hash": "7e6fdaa3abc8d03c",
      "childrenByOrder": {}
    },
    {
      "rendered": true,
      "initial": false,
      "entry": false,
      "recorded": false,
      "size": 1285,
      "sizes": {
        "javascript": 1285
      },
      "names": [],
      "idHints": [],
      "runtime": [
        "@openmrs/esm-patient-notes-app",
        "main"
      ],
      "files": [
        "788.js"
      ],
      "auxiliaryFiles": [],
      "hash": "c964c4bd9b79c887",
      "childrenByOrder": {}
    },
    {
      "rendered": true,
      "initial": false,
      "entry": false,
      "recorded": false,
      "size": 1505,
      "sizes": {
        "javascript": 1505
      },
      "names": [],
      "idHints": [],
      "runtime": [
        "@openmrs/esm-patient-notes-app",
        "main"
      ],
      "files": [
        "807.js"
      ],
      "auxiliaryFiles": [],
      "hash": "9fbe2bc030dcf097",
      "childrenByOrder": {}
    },
    {
      "rendered": true,
      "initial": false,
      "entry": false,
      "recorded": false,
      "size": 1154,
      "sizes": {
        "javascript": 1154
      },
      "names": [],
      "idHints": [],
      "runtime": [
        "@openmrs/esm-patient-notes-app",
        "main"
      ],
      "files": [
        "833.js"
      ],
      "auxiliaryFiles": [],
      "hash": "b996f90855b5b66a",
      "childrenByOrder": {}
    },
    {
      "rendered": true,
      "initial": false,
      "entry": false,
      "recorded": false,
      "size": 7160,
      "sizes": {
        "javascript": 7160
      },
      "names": [],
      "idHints": [],
      "runtime": [
        "@openmrs/esm-patient-notes-app",
        "main"
      ],
      "files": [
        "879.js"
      ],
      "auxiliaryFiles": [
        "879.js.map"
      ],
      "hash": "f087e999a3033119",
      "childrenByOrder": {}
    }
  ]
}